koekiemonster/__init__.py
koekiemonster-0.0.1.dist-info/METADATA
koekiemonster-0.0.1.dist-info/RECORD
koekiemonster-0.0.1.dist-info/WHEEL
koekiemonster-0.0.1.dist-info/top_level.txt
