Metadata-Version: 2.1
Name: koekiemonster
Version: 0.0.1
Summary: Koekie Monster loads cookies from FireFox, allowing you to easily use your session cookies programatically.
Home-page: https://github.com/glennzw/koekiemonster
Author: Glenn Wilkinson
Author-email: glennzw@protonmail.com
License: UNKNOWN
Platform: UNKNOWN
Classifier: Programming Language :: Python :: 2.7
Classifier: License :: OSI Approved :: MIT License
Classifier: Operating System :: OS Independent
